platzky_login_with_google/__init__.py
platzky_login_with_google/entrypoint.py
platzky_login_with_google/login_with_google.html
platzky_login_with_google/logout_with_google.html
platzky_login_with_google-0.3.0.dist-info/METADATA
platzky_login_with_google-0.3.0.dist-info/WHEEL
platzky_login_with_google-0.3.0.dist-info/licenses/LICENSE
platzky_login_with_google-0.3.0.dist-info/RECORD
